vlogs/__init__.py
vlogs/config.py
vlogs/model.py
vlogs/sdk.py
vlogs/service.py
vlogs/util.py
vlogs-1.0.6.dist-info/METADATA
vlogs-1.0.6.dist-info/WHEEL
vlogs-1.0.6.dist-info/RECORD
