Metadata-Version: 2.1
Name: vlogs
Version: 1.0.6
Summary: CUBETIQ vLogs SDK for Python
License: MIT
Author: Sambo Chea
Author-email: sombochea@cubetiqs.com
Requires-Python: >=3.10,<4.0
Classifier: License :: OSI Approved :: MIT License
Classifier: Programming Language :: Python :: 3
Classifier: Programming Language :: Python :: 3.10
Classifier: Programming Language :: Python :: 3.11
Requires-Dist: httpx (>=0.24.1,<0.25.0)
